Metadata-Version: 2.1
Name: topsis-101703191
Version: 0.0.1
Summary: TOPSIS method
Home-page: https://github.com/geetanshg22/topsis
Author: Geetansh Goyal
Author-email: ggoyal_be17@thapar.edu
License: UNKNOWN
Platform: UNKNOWN
Classifier: Programming Language :: Python :: 3
Classifier: License :: OSI Approved :: MIT License
Classifier: Operating System :: OS Independent
Requires-Dist: scipy
Requires-Dist: tabulate
Requires-Dist: numpy
Requires-Dist: pandas
